ideabox.theme-1.0.3-py3.10-nspkg.pth
ideabox/theme/DEVELOP_THEME.rst
ideabox/theme/__init__.py
ideabox/theme/configure.zcml
ideabox/theme/interfaces.py
ideabox/theme/permissions.zcml
ideabox/theme/setuphandlers.py
ideabox/theme/testing.py
ideabox/theme/upgrades.py
ideabox/theme/upgrades.zcml
ideabox/theme/browser/__init__.py
ideabox/theme/browser/configure.zcml
ideabox/theme/browser/overrides/.gitkeep
ideabox/theme/browser/static/.gitkeep
ideabox/theme/locales/README.rst
ideabox/theme/locales/__init__.py
ideabox/theme/locales/ideabox.theme.pot
ideabox/theme/locales/update.py
ideabox/theme/locales/update.sh
ideabox/theme/locales/en/LC_MESSAGES/ideabox.theme.po
ideabox/theme/profiles/default/browserlayer.xml
ideabox/theme/profiles/default/catalog.xml
ideabox/theme/profiles/default/metadata.xml
ideabox/theme/profiles/default/registry.xml
ideabox/theme/profiles/default/rolemap.xml
ideabox/theme/profiles/default/theme.xml
ideabox/theme/profiles/uninstall/browserlayer.xml
ideabox/theme/profiles/uninstall/theme.xml
ideabox/theme/tests/__init__.py
ideabox/theme/tests/test_robot.py
ideabox/theme/tests/test_setup.py
ideabox/theme/tests/robot/test_example.robot
ideabox/theme/theme/backend.xml
ideabox/theme/theme/barceloneta-apple-touch-icon-114x114-precomposed.png
ideabox/theme/theme/barceloneta-apple-touch-icon-144x144-precomposed.png
ideabox/theme/theme/barceloneta-apple-touch-icon-57x57-precomposed.png
ideabox/theme/theme/barceloneta-apple-touch-icon-72x72-precomposed.png
ideabox/theme/theme/barceloneta-apple-touch-icon-precomposed.png
ideabox/theme/theme/barceloneta-apple-touch-icon.png
ideabox/theme/theme/barceloneta-favicon.ico
ideabox/theme/theme/index.html
ideabox/theme/theme/manifest.cfg
ideabox/theme/theme/package.json
ideabox/theme/theme/preview.png
ideabox/theme/theme/rules.xml
ideabox/theme/theme/barceloneta/BARCELONETA-UPDATE.rst
ideabox/theme/theme/barceloneta/BARCELONETA-VERSION.rst
ideabox/theme/theme/barceloneta/backend.xml
ideabox.theme-1.0.3.dist-info/LICENSE.GPL
ideabox.theme-1.0.3.dist-info/LICENSE.rst
ideabox.theme-1.0.3.dist-info/METADATA
ideabox.theme-1.0.3.dist-info/WHEEL
ideabox.theme-1.0.3.dist-info/entry_points.txt
ideabox.theme-1.0.3.dist-info/namespace_packages.txt
ideabox.theme-1.0.3.dist-info/top_level.txt
ideabox.theme-1.0.3.dist-info/RECORD
