Metadata-Version: 2.1
Name: ideabox.theme
Version: 1.0.3
Summary: An add-on for Plone
Home-page: https://github.com/imio/ideabox.theme
Author: Benoit Suttor
Author-email: bsuttor@imio.be
License: GPL version 2
Project-URL: PyPI, https://pypi.python.org/pypi/ideabox.theme
Project-URL: Source, https://github.com/imio/ideabox.theme
Project-URL: Tracker, https://github.com/imio/ideabox.theme/issues
Keywords: Python Plone
Classifier: Environment :: Web Environment
Classifier: Framework :: Plone
Classifier: Framework :: Plone :: Addon
Classifier: Framework :: Plone :: 5.1
Classifier: Programming Language :: Python
Classifier: Programming Language :: Python :: 3.8
Classifier: Operating System :: OS Independent
Classifier: License :: OSI Approved :: GNU General Public License v2 (GPLv2)
Requires-Python: >=3.8
License-File: LICENSE.GPL
License-File: LICENSE.rst
Requires-Dist: setuptools
Requires-Dist: plone.app.themingplugins
Requires-Dist: collective.themefragments
Requires-Dist: z3c.jbot
Requires-Dist: plone.api (>=1.8.4)
Requires-Dist: plone.restapi
Requires-Dist: plone.app.dexterity
Provides-Extra: test
Requires-Dist: plone.app.testing ; extra == 'test'
Requires-Dist: plone.testing (>=5.0.0) ; extra == 'test'
Requires-Dist: plone.app.contenttypes ; extra == 'test'
Requires-Dist: plone.app.robotframework[debug] ; extra == 'test'
